processor/regfile/regfile.sv
module regfile #(
    parameter XLEN = 32, // REgister size 
    parameter NREG = 32  // number of registers
)(
    input  logic             clk,
    input  logic             write_enable,	// write enable
    input  logic [4:0]       reg_src_1,		// source register 1
    input  logic [4:0]       reg_src_2,		// source register 2
    input  logic [4:0]       reg_dest,		// destination register
    input  logic [XLEN-1:0]  write_data,    // write data
    output logic [XLEN-1:0]  read_data_1,   // read data 1
    output logic [XLEN-1:0]  read_data_2    // read data 2
);

    // register storage
    logic [XLEN-1:0] registers [NREG-1:0]; 

	// Async reads
	// supply outputs constantly and as fast as possible
    always_comb begin
		// This enforces x0 = 0 always 
        read_data_1 = (reg_src_1 == 5'd0) ? '0 : registers[reg_src_1];
        read_data_2 = (reg_src_2 == 5'd0) ? '0 : registers[reg_src_2]; 
    end
	
	// sync writes
	// Only modify inputs on clk edge
    always_ff @(posedge clk) begin
        if (write_enable && (reg_dest != 5'd0)) // Don't write to x0
            registers[reg_dest] <= write_data;
    end

endmodule

processor/regfile/tb_regfile.sv
`timescale 1ns/1ps

module tb_regfile;
	
	logic clk, write_enable;
	logic[4:0] reg_src_1, reg_src_2, reg_dest;
	logic[31:0] write_data, read_data_1, read_data_2;
	
	localparam XLEN = 32;
	localparam NREG = 32;

	regfile #(
		.XLEN(XLEN),
		.NREG(NREG)
	) dut (
		// .submodule_port(outer_module_port)
		.clk(clk),
		.write_enable(write_enable),
		.reg_src_1(reg_src_1),
		.reg_src_2(reg_src_2),
		.reg_dest(reg_dest),
		.write_data(write_data),
		.read_data_1(read_data_1),
		.read_data_2(read_data_2)
	);

	initial clk = 0;
	always # 5 clk = ~clk;
	

	task automatic check_equal(
		input logic[XLEN-1:0]	actual,
		input logic[XLEN-1:0]	expected,
		input string			msg
	);
	begin 
		if (actual !== expected) begin // ! = = catches Xs as well
			$display("ERROR %s | expected = 0x%08h, got = 0x%08h", msg, expected, actual);
			$fatal;
		end 
		else begin 
			$display("PASS: %s | value = 0x%08h", msg, actual);
		end
	end
	endtask

	initial begin 
		$dumpfile("out/regfile.vcd");
        $dumpvars(0, tb_regfile);

		$display("Starting Regfile Verification");
		// Initialize inputs
        write_enable  = 0;
        reg_src_1 = 0;
        reg_src_2 = 0;
        reg_dest = 0;
        write_data  = 0;
	
		// test one, check if x0 == 0 
		reg_src_1 = 5'd0;
		reg_src_2 = 5'd0; 
		#1 // Delay clock
		check_equal(read_data_1, 32'h0000_0000, "x0 read on port 1 is zero");
		check_equal(read_data_2, 32'h0000_0000, "x0 read on port 2 is zero");

		// test 2, write/read reg 1
		@(negedge clk);
		write_enable = 1;
		reg_dest = 5'd1;
		write_data = 32'h12345678;

		@(posedge clk);
		reg_src_1 = 5'd1;
		#1;
		write_enable = 0;
		check_equal(read_data_1, 32'h12345678, "write/read x1");

		// test 3, write to x2, read both ports 
		@(negedge clk); 
		write_enable = 1;
		reg_dest = 5'd2;
		write_data = 32'hABAB0011;

		@(posedge clk);
		reg_src_1 = 5'd1;
		reg_src_2 = 5'd2;
		#1;
		check_equal(read_data_1, 32'h12345678, "read x1 on port 1");
		check_equal(read_data_2, 32'hABAB0011, "read x2 on port 2");

		write_enable = 0;
		// test 4, attempt to write to x0
		@(negedge clk);
		write_enable=1;
		reg_dest = 5'd0;
		write_data = 32'hFFFF_FFFF;

		@(posedge clk);
		reg_src_1 = 5'd0;
		#1;
		write_enable = 0;
		check_equal(read_data_1, 32'h0000_0000, "check overwrite x0");

		// test 5: overwrite x1:

		@(negedge clk);
		write_enable = 1;
		reg_dest = 5'd1;
		write_data = 32'hFAFA_FEFE;

		@(posedge clk);
		reg_src_1 = 5'd1;
		#1;
		write_enable = 0;
		check_equal(read_data_1, 32'hFAFA_FEFE, "Overwrite x1");

		$display("All Tests Passed.");
		$finish;
	end
endmodule

processor/regfile/out/regfile.vcd
$date
	Wed Mar 11 22:17:10 2026
$end
$version
	Icarus Verilog
$end
$timescale
	1ps
$end
$scope module tb_regfile $end
$var wire 32 ! read_data_2 [31:0] $end
$var wire 32 " read_data_1 [31:0] $end
$var parameter 32 # NREG $end
$var parameter 32 $ XLEN $end
$var reg 1 % clk $end
$var reg 5 & reg_dest [4:0] $end
$var reg 5 ' reg_src_1 [4:0] $end
$var reg 5 ( reg_src_2 [4:0] $end
$var reg 32 ) write_data [31:0] $end
$var reg 1 * write_enable $end
$scope module dut $end
$var wire 1 % clk $end
$var wire 5 + reg_dest [4:0] $end
$var wire 5 , reg_src_1 [4:0] $end
$var wire 5 - reg_src_2 [4:0] $end
$var wire 32 . write_data [31:0] $end
$var wire 1 * write_enable $end
$var parameter 32 / NREG $end
$var parameter 32 0 XLEN $end
$var reg 32 1 read_data_1 [31:0] $end
$var reg 32 2 read_data_2 [31:0] $end
$upscope $end
$scope task check_equal $end
$upscope $end
$upscope $end
$enddefinitions $end
$comment Show the parameter values. $end
$dumpall
b100000 0
b100000 /
b100000 $
b100000 #
$end
#0
$dumpvars
b0 2
b0 1
b0 .
b0 -
b0 ,
b0 +
0*
b0 )
b0 (
b0 '
b0 &
0%
b0 "
b0 !
$end
#5000
1%
#10000
b10010001101000101011001111000 )
b10010001101000101011001111000 .
b1 &
b1 +
1*
0%
#15000
b10010001101000101011001111000 "
b10010001101000101011001111000 1
b1 '
b1 ,
1%
#16000
0*
#20000
b10101011101010110000000000010001 )
b10101011101010110000000000010001 .
b10 &
b10 +
1*
0%
#25000
b10101011101010110000000000010001 !
b10101011101010110000000000010001 2
b10 (
b10 -
1%
#26000
0*
#30000
b11111111111111111111111111111111 )
b11111111111111111111111111111111 .
b0 &
b0 +
1*
0%
#35000
b0 "
b0 1
b0 '
b0 ,
1%
#36000
0*
#40000
b11111010111110101111111011111110 )
b11111010111110101111111011111110 .
b1 &
b1 +
1*
0%
#45000
b11111010111110101111111011111110 "
b11111010111110101111111011111110 1
b1 '
b1 ,
1%
#46000
0*
