processor/alu/alu.sv
module alu (
    input  logic [31:0] a,
    input  logic [31:0] b,
    input  logic [3:0]  alu_op,
    output logic [31:0] result,
    output logic        zero
);

    // Only lower 5 bits used for shift amount in RV32
    logic [4:0] shamt;
    assign shamt = b[4:0];

    // ALU op encodings
    localparam logic [3:0]
        ALU_ADD  = 4'd0,
        ALU_SUB  = 4'd1,
        ALU_AND  = 4'd2,
        ALU_OR   = 4'd3,
        ALU_XOR  = 4'd4,
        ALU_SLL  = 4'd5,
        ALU_SRL  = 4'd6,
        ALU_SRA  = 4'd7,
        ALU_SLT  = 4'd8,
        ALU_SLTU = 4'd9;

    // Intermediate results
    logic [31:0] add_r, sub_r, and_r, or_r, xor_r;
    logic [31:0] sll_r, srl_r, sra_r;
    logic [31:0] slt_r, sltu_r;

    // Arithmetic / logic
    assign add_r = a + b;
    assign sub_r = a - b;
    assign and_r = a & b;
    assign or_r  = a | b;
    assign xor_r = a ^ b;

    // Shifts
    assign sll_r = a << shamt;
    assign srl_r = a >> shamt;
    assign sra_r = $signed(a) >>> shamt;

    // Comparisons (RISC-V returns 0 or 1)
    assign slt_r  = ($signed(a) < $signed(b)) ? 32'd1 : 32'd0;
    assign sltu_r = (a < b)                   ? 32'd1 : 32'd0;

    // Result mux
    always_comb begin
        case (alu_op)
            ALU_ADD:  result = add_r;
            ALU_SUB:  result = sub_r;
            ALU_AND:  result = and_r;
            ALU_OR:   result = or_r;
            ALU_XOR:  result = xor_r;
            ALU_SLL:  result = sll_r;
            ALU_SRL:  result = srl_r;
            ALU_SRA:  result = sra_r;
            ALU_SLT:  result = slt_r;
            ALU_SLTU: result = sltu_r;
            default:  result = 32'd0;
        endcase
    end

    // Zero flag (used for BEQ in CPUs)
    assign zero = ~(|result);

endmodule

processor/alu/tb_alu.sv
`timescale 1ns/1ps

module tb_alu;

   logic [31:0] a, b;
   logic [3:0]  alu_op;
   logic [31:0] result;
   logic        zero;

   localparam logic [3:0]
       ALU_ADD  = 4'd0,
       ALU_SUB  = 4'd1,
       ALU_AND  = 4'd2,
       ALU_OR   = 4'd3,
       ALU_XOR  = 4'd4,
       ALU_SLL  = 4'd5,
       ALU_SRL  = 4'd6,
       ALU_SRA  = 4'd7,
       ALU_SLT  = 4'd8,
       ALU_SLTU = 4'd9;

   // DUT (module name is alu)
   alu dut (
       .a(a),
       .b(b),
       .alu_op(alu_op),
       .result(result),
       .zero(zero)
   );

   // ------------------------------------------------------------
   // Golden model: compute expected ALU output from a/b/op
   // (matches your ALU design where shamt = b[4:0])
   // ------------------------------------------------------------
   function automatic [31:0] alu_model(
       input [31:0] a_in,
       input [31:0] b_in,
       input [3:0]  op_in
   );
       logic [4:0] shamt;
       begin
           shamt = b_in[4:0];
           case (op_in)
               ALU_ADD:  alu_model = a_in + b_in;
               ALU_SUB:  alu_model = a_in - b_in;
               ALU_AND:  alu_model = a_in & b_in;
               ALU_OR:   alu_model = a_in | b_in;
               ALU_XOR:  alu_model = a_in ^ b_in;
               ALU_SLL:  alu_model = a_in << shamt;
               ALU_SRL:  alu_model = a_in >> shamt;
               ALU_SRA:  alu_model = $signed(a_in) >>> shamt;
               ALU_SLT:  alu_model = ($signed(a_in) < $signed(b_in)) ? 32'd1 : 32'd0;
               ALU_SLTU: alu_model = (a_in < b_in) ? 32'd1 : 32'd0;
               default:  alu_model = 32'd0;
           endcase
       end
   endfunction

   // Your original directed check (kept)
   task check;
       input [31:0]  exp;
       input [127:0] name;
       begin
           #1;
           if (result !== exp) begin
               $display("FAIL %0s  a=%h b=%h op=%0d got=%h exp=%h",
                        name, a, b, alu_op, result, exp);
               $finish;
           end
           if (zero !== (exp == 0)) begin
               $display("FAIL ZERO %0s got_zero=%b exp_zero=%b",
                        name, zero, (exp == 0));
               $finish;
           end
           $display("PASS %0s result=%h zero=%b", name, result, zero);
       end
   endtask

   // New: automatic check that uses the golden model
   task check_model;
       input [127:0] name;
       logic [31:0] exp;
       begin
           exp = alu_model(a, b, alu_op);
           check(exp, name);
       end
   endtask

   integer i;

   initial begin
       $dumpfile("out/alu.vcd");
       $dumpvars(0, tb_alu);

       // ----------------
       // Directed tests
       // ----------------
       a = 32'd10; b = 32'd7; alu_op = ALU_ADD;
       check_model("ADD");

       a = 32'd123; b = 32'd123; alu_op = ALU_SUB;
       check_model("SUBeq");

       a = 32'hAA00_F0F0; b = 32'h0F0F_00FF; alu_op = ALU_AND;
       check_model("AND");

       a = 32'hAA00_F0F0; b = 32'h0F0F_00FF; alu_op = ALU_OR;
       check_model("OR");

       a = 32'hAA00_F0F0; b = 32'h0F0F_00FF; alu_op = ALU_XOR;
       check_model("XOR");

       a = 32'h0000_0001; b = 32'd8; alu_op = ALU_SLL;
       check_model("SLL");

       a = 32'h8000_0000; b = 32'd1; alu_op = ALU_SRL;
       check_model("SRL");

       a = 32'h8000_0000; b = 32'd1; alu_op = ALU_SRA;
       check_model("SRA");

       a = 32'hFFFF_FFFF; b = 32'd1; alu_op = ALU_SLT;
       check_model("SLT");

       a = 32'hFFFF_FFFF; b = 32'd1; alu_op = ALU_SLTU;
       check_model("SLTU");

       // ----------------
       // Randomized tests
       // ----------------
       for (i = 0; i < 2000; i = i + 1) begin
           a = $random;
           b = $random;
           alu_op = $random % 10;
           check_model("RND");
       end

       $display("ALL TESTS PASSED (directed + random)");
       #5 $finish;
   end

endmodule

processor/out/alu.vcd
$date
	Thu Mar  5 12:17:03 2026
$end
$version
	Icarus Verilog
$end
$timescale
	1ps
$end
$scope module tb_alu $end
$var wire 1 ! zero $end
$var wire 32 " result [31:0] $end
$var parameter 4 # ALU_ADD $end
$var parameter 4 $ ALU_AND $end
$var parameter 4 % ALU_OR $end
$var parameter 4 & ALU_SLL $end
$var parameter 4 ' ALU_SLT $end
$var parameter 4 ( ALU_SLTU $end
$var parameter 4 ) ALU_SRA $end
$var parameter 4 * ALU_SRL $end
$var parameter 4 + ALU_SUB $end
$var parameter 4 , ALU_XOR $end
$var reg 32 - a [31:0] $end
$var reg 4 . alu_op [3:0] $end
$var reg 32 / b [31:0] $end
$var integer 32 0 i [31:0] $end
$scope function alu_model $end
$upscope $end
$scope module dut $end
$var wire 32 1 a [31:0] $end
$var wire 4 2 alu_op [3:0] $end
$var wire 32 3 and_r [31:0] $end
$var wire 32 4 b [31:0] $end
$var wire 32 5 or_r [31:0] $end
$var wire 32 6 xor_r [31:0] $end
$var wire 1 ! zero $end
$var wire 32 7 sub_r [31:0] $end
$var wire 32 8 srl_r [31:0] $end
$var wire 32 9 sra_r [31:0] $end
$var wire 32 : sltu_r [31:0] $end
$var wire 32 ; slt_r [31:0] $end
$var wire 32 < sll_r [31:0] $end
$var wire 5 = shamt [4:0] $end
$var wire 32 > add_r [31:0] $end
$var parameter 4 ? ALU_ADD $end
$var parameter 4 @ ALU_AND $end
$var parameter 4 A ALU_OR $end
$var parameter 4 B ALU_SLL $end
$var parameter 4 C ALU_SLT $end
$var parameter 4 D ALU_SLTU $end
$var parameter 4 E ALU_SRA $end
$var parameter 4 F ALU_SRL $end
$var parameter 4 G ALU_SUB $end
$var parameter 4 H ALU_XOR $end
$var reg 32 I result [31:0] $end
$upscope $end
$scope task check $end
$var reg 32 J exp [31:0] $end
$var reg 128 K name [127:0] $end
$upscope $end
$scope task check_model $end
$var reg 32 L exp [31:0] $end
$var reg 128 M name [127:0] $end
$upscope $end
$upscope $end
$enddefinitions $end
$comment Show the parameter values. $end
$dumpall
b100 H
b1 G
b110 F
b111 E
b1001 D
b1000 C
b101 B
b11 A
b10 @
b0 ?
b100 ,
b1 +
b110 *
b111 )
b1001 (
b1000 '
b101 &
b11 %
b10 $
b0 #
$end
#0
$dumpvars
b10000010100010001000100 M
b10001 L
b10000010100010001000100 K
b10001 J
b10001 I
b10001 >
b111 =
b10100000000 <
b0 ;
b0 :
b0 9
b0 8
b11 7
b1101 6
b1111 5
b111 4
b10 3
b0 2
b1010 1
bx 0
b111 /
b0 .
b1010 -
b10001 "
0!
$end
#1000
1!
b11011 =
b1111011 3
b1111011 5
b0 6
b0 "
b0 I
b101001101010101010000100110010101110001 K
b0 J
b0 L
b101001101010101010000100110010101110001 M
b1 .
b1 2
b1111011 /
b1111011 4
b11110110 >
b0 7
b11011000000000000000000000000000 <
b1111011 -
b1111011 1
#2000
0!
b11111 =
b1010000000000000000011110000 3
b10101111000011111111000011111111 5
b10100101000011111111000000001111 6
b1010000000000000000011110000 "
b1010000000000000000011110000 I
b1 ;
b10000010100111001000100 K
b1010000000000000000011110000 J
b1010000000000000000011110000 L
b10000010100111001000100 M
b10 .
b10 2
b1111000011110000000011111111 /
b1111000011110000000011111111 4
b10111001000011111111000111101111 >
b10011010111100011110111111110001 7
b0 <
b1 8
b11111111111111111111111111111111 9
b10101010000000001111000011110000 -
b10101010000000001111000011110000 1
#3000
b10101111000011111111000011111111 "
b10101111000011111111000011111111 I
b100111101010010 K
b10101111000011111111000011111111 J
b10101111000011111111000011111111 L
b100111101010010 M
b11 .
b11 2
#4000
b10100101000011111111000000001111 "
b10100101000011111111000000001111 I
b10110000100111101010010 K
b10100101000011111111000000001111 J
b10100101000011111111000000001111 L
b10110000100111101010010 M
b100 .
b100 2
#5000
b1000 =
b0 3
b1001 5
b1001 6
b100000000 "
b100000000 I
b1 :
b10100110100110001001100 K
b100000000 J
b100000000 L
b10100110100110001001100 M
b101 .
b101 2
b1000 /
b1000 4
b1001 >
b11111111111111111111111111111001 7
b100000000 <
b0 8
b0 9
b1 -
b1 1
#6000
b1 =
b10000000000000000000000000000001 5
b10000000000000000000000000000001 6
b1000000000000000000000000000000 "
b1000000000000000000000000000000 I
b0 :
b10100110101001001001100 K
b1000000000000000000000000000000 J
b1000000000000000000000000000000 L
b10100110101001001001100 M
b110 .
b110 2
b1 /
b1 4
b10000000000000000000000000000001 >
b1111111111111111111111111111111 7
b0 <
b1000000000000000000000000000000 8
b11000000000000000000000000000000 9
b10000000000000000000000000000000 -
b10000000000000000000000000000000 1
#7000
b11000000000000000000000000000000 "
b11000000000000000000000000000000 I
b10100110101001001000001 K
b11000000000000000000000000000000 J
b11000000000000000000000000000000 L
b10100110101001001000001 M
b111 .
b111 2
#8000
b1 3
b11111111111111111111111111111111 5
b11111111111111111111111111111110 6
b1 "
b1 I
b10100110100110001010100 K
b1 J
b1 L
b10100110100110001010100 M
b1000 .
b1000 2
b0 >
b11111111111111111111111111111110 7
b11111111111111111111111111111110 <
b1111111111111111111111111111111 8
b11111111111111111111111111111111 9
b11111111111111111111111111111111 -
b11111111111111111111111111111111 1
#9000
1!
b0 "
b0 I
b1010011010011000101010001010101 K
b0 J
b0 L
b1010011010011000101010001010101 M
b1001 .
b1001 2
#10000
0!
b1 :
b10001010000000000 3
b11010010100111010111111110100101 5
b11010010100111000110101110100101 6
b1001000010101001101010010010 "
b1001000010101001101010010010 I
b0 ;
b10100100100111001000100 K
b1001000010101001101010010010 J
b1001000010101001101010010010 L
b10100100100111001000100 M
b111 .
b111 2
b11000000100010010101111010000001 /
b11000000100010010101111010000001 4
b11010010100111101001001110100101 >
b1010001100010111101011010100011 7
b100100001010100110101001001000 <
b1001000010101001101010010010 8
b1001000010101001101010010010 9
b10010000101010011010100100100 -
b10010000101010011010100100100 1
b0 0
#11000
b1101 =
b0 :
b101100000101001000000001 3
b10110111111110010111111101101111 5
b10110111010010010010110101101110 6
b11111111111111011000111110000010 "
b11111111111111011000111110000010 I
b1 ;
b11111111111111011000111110000010 J
b11111111111111011000111110000010 L
b110101110010111101100001101 /
b110101110010111101100001101 4
b10111000101010011101000101110000 >
b10101011001101101101101101010110 7
b1010110011000110000000000000 <
b1011000111110000010 8
b11111111111111011000111110000010 9
b10110001111100000101011001100011 -
b10110001111100000101011001100011 1
b1 0
#12000
b10010 =
b0 ;
b10000000000000100000000000000000 3
b10111011111101111101011001110111 5
b111011111101011101011001110111 6
b101001100010110011001001010011 "
b101001100010110011001001010011 I
b101001100010110011001001010011 J
b101001100010110011001001010011 L
b1 .
b1 2
b10001001001101110101001000010010 /
b10001001001101110101001000010010 4
b111011111110011101011001110111 >
b101001100010110011001001010011 7
b10001100101000000000000000000 <
b10110010110000 8
b11111111111111111110110010110000 9
b10110010110000101000010001100101 -
b10110010110000101000010001100101 1
b10 0
#13000
b10110 =
b1 ;
b10000000111100000100000100 3
b111111111101111111110101111111 5
b111101111101000011110001111011 6
b11011 "
b11011 I
b1 :
b11011 J
b11011 L
b111 .
b111 2
b111011001000111111000101110110 /
b111011001000111111000101110110 4
b1000001111110111011111010000011 >
b11001011101100111101101110010111 7
b1000011010000000000000000000000 <
b11011 8
b11011 9
b110110101111100110100001101 -
b110110101111100110100001101 1
b11 0
#14000
1!
b1100 =
b1000110000001000101011110001100 3
b1110110111111011111011111101101 5
b110000111110011010000001100001 6
b0 "
b0 I
b0 ;
b0 :
b0 J
b0 L
b1001 .
b1001 2
b1000110001011011111011110001100 /
b1000110001011011111011110001100 4
b10111101000000100100111101111001 >
b110000101001100110000001100001 7
b1000101011111101101000000000000 <
b1110110110101000101 8
b1110110110101000101 9
b1110110110101000101011111101101 -
b1110110110101000101011111101101 1
b100 0
#15000
b101 =
b11100010001101110000010011000100 3
b11100011111101111010010011000111 5
b1110000001010000000000011 6
b1100 .
b1100 2
b11100010111101111000010011000101 /
b11100010111101111000010011000101 4
b11000110001011101010100110001011 >
b1111111010000000000001 7
b1100110111001001001100011000000 <
b111000110011011100100100110 8
b11111111000110011011100100100110 9
b11100011001101110010010011000110 -
b11100011001101110010010011000110 1
b101 0
#16000
b10111 =
b110010100000100111001001100101 3
b11111011111111111111011111110111 5
b11001001011111011000010110010010 6
b1 :
b1110 .
b1110 2
b10111011110100100111001001110111 /
b10111011110100100111001001110111 4
b101110100000100110101001011100 >
b10110110110111011000010101101110 7
b11110010100000000000000000000000 <
b11100101 8
b11100101 9
b1110010101011111111011111100101 -
b1110010101011111111011111100101 1
b110 0
#17000
b10010 =
b1 ;
b1000001001000000100100110000010 3
b1111111111111001111101111111111 5
b111110110111001011001001111101 6
b1010 .
b1010 2
b1111001001100000110100111110010 /
b1111001001100000110100111110010 4
b11000001000111010100010110000001 >
b11001110101111000111000110011101 7
b1101110001111000000000000000000 <
b1000111111011 8
b1000111111011 9
b1000111111011001101101110001111 -
b1000111111011001101101110001111 1
b111 0
#18000
0!
b101 =
b0 ;
b11100000000000000100101011000000 3
b11110110110010100111111011101101 5
b10110110010100011010000101101 6
b10110110010100011010000101101 "
b10110110010100011010000101101 I
b0 :
b10110110010100011010000101101 J
b10110110010100011010000101101 L
b100 .
b100 2
b11100010110010100100111011000101 /
b11100010110010100100111011000101 4
b11010110110010101100100110101101 >
b10001001101100010110000100011 7
b10000000000011110101110100000000 <
b111101000000000001111010111 8
b11111111101000000000001111010111 9
b11110100000000000111101011101000 -
b11110100000000000111101011101000 1
b1000 0
#19000
1!
b1101 =
b10010110100010100000100000101101 3
b11011110101011110111100010111101 5
b1001000001001010111000010010000 6
b0 "
b0 I
b0 J
b0 L
b1001 .
b1001 2
b10010110101010110101100000101101 /
b10010110101010110101100000101101 4
b1110101001110011000000011101010 >
b1000111111000101101000010010000 7
b11000101000101111010000000000000 <
b1101111010001110001 8
b11111111111111101111010001110001 9
b11011110100011100010100010111101 -
b11011110100011100010100010111101 1
b1001 0
#20000
0!
b1 "
b1 I
b1010 =
b1 ;
b1011000110000001000000010 3
b10110101111111111110011101101011 5
b10110100100111001110010101101001 6
b1 J
b1 L
b1000 .
b1000 2
b101011100111000011100001010 /
b101011100111000011100001010 4
b10110111011000101110100101101101 >
b10101100011110111101101101011001 7
b10111101100010011000110000000000 <
b1011000111101111011000 8
b11111111111011000111101111011000 9
b10110001111011110110001001100011 -
b10110001111011110110001001100011 1
b1010 0
#21000
1!
b1 :
b10000011000000000000100100000 3
b1010101011111000110010110101010 5
b1000101000111000110010010001010 6
b0 "
b0 I
b0 J
b0 L
b1011 .
b1011 2
b1010101011110000100010110101010 /
b1010101011110000100010110101010 4
b1100101110111000110011011001010 >
b10111010111010111101101101110110 7
b10010000100001001000000000000000 <
b1000001100100001000 8
b1000001100100001000 9
b10000011001000010000100100000 -
b10000011001000010000100100000 1
b1011 0
#22000
b10011 =
b0 ;
b10001001000000000011100000010010 3
b11001011101000111011111010010111 5
b1000010101000111000011010000101 6
b0 :
b10001001100000111011100000010011 /
b10001001100000111011100000010011 4
b1010100101000111111011010101001 >
b1000001100111001000011010000011 7
b11110100101100000000000000000000 <
b1100101100100 8
b11111111111111111111100101100100 9
b11001011001000000011111010010110 -
b11001011001000000011111010010110 1
b1100 0
#23000
b1011 =
b1 ;
b100001100001111101010001000011 3
b10111101101111111101111101111011 5
b10011100001110000000101100111000 6
b1111 .
b1111 2
b110101100111111101110101101011 /
b110101100111111101110101101011 4
b11011111010001111011001110111110 >
b1110100000001111111100011101000 7
b111110101100101001100000000000 <
b101010011010011111010 8
b11111111111101010011010011111010 9
b10101001101001111101011001010011 -
b10101001101001111101011001010011 1
b1101 0
#24000
0!
b1110 =
b1 :
b10000001000101100000101000000010 3
b11010111010101110111111010101110 5
b1010110010000010111010010101100 6
b10101001110000010000101101010100 "
b10101001110000010000101101010100 I
b10101001110000010000101101010100 J
b10101001110000010000101101010100 L
b1 .
b1 2
b11010111010101100011111010101110 /
b11010111010101100011111010101110 4
b1011000011011011000100010110000 >
b10101001110000010000101101010100 7
b11010010100000001000000000000000 <
b100000010001011101 8
b11111111111111100000010001011101 9
b10000001000101110100101000000010 -
b10000001000101110100101000000010 1
b1110 0
#25000
b11 =
b1100001000100000000000011 3
b11110111110001010111101111101111 5
b11110110010000010011101111101100 6
b11111001010010011011101111110010 "
b11111001010010011011101111110010 I
b0 :
b11111001010010011011101111110010 J
b11111001010010011011101111110010 L
b0 .
b0 2
b10001100001000100100100100011 /
b10001100001000100100100100011 4
b11111001010010011011101111110010 >
b11010110010000010010100110101100 7
b111110001010111001011001111000 <
b11100111110001010111001011001 8
b11111100111110001010111001011001 9
b11100111110001010111001011001111 -
b11100111110001010111001011001111 1
b1111 0
#26000
b11100 =
b0 ;
b10000100001100010000100000001000 3
b11111111011100110100111011111110 5
b1111011010000100100011011110110 6
b1110 "
b1110 I
b1110 J
b1110 L
b110 .
b110 2
b10011110001100010100110000111100 /
b10011110001100010100110000111100 4
b10000011101001000101011100000110 >
b1000111010000011011111010001110 7
b10100000000000000000000000000000 <
b1110 8
b11111111111111111111111111111110 9
b11100101011100110000101011001010 -
b11100101011100110000101011001010 1
b10000 0
#27000
1!
b10001010010111001100001100010100 <
b1 =
b1000010000100000000 3
b1100101111011101111001111001011 5
b1100101111010101101001011001011 6
b0 "
b0 I
b0 J
b0 L
b1110 .
b1110 2
b100000110001001011001101000001 /
b100000110001001011001101000001 4
b1100101111100110001010011001011 >
b100100011010011010111001001001 7
b100010100101110011000011000101 8
b100010100101110011000011000101 9
b1000101001011100110000110001010 -
b1000101001011100110000110001010 1
b10001 0
#28000
0!
b1001 =
b1 :
b100000000000001001000001000 3
b11111100101010101111001111111001 5
b11111000101010101110000111110001 6
b111100001000001111001 "
b111100001000001111001 I
b111100001000001111001 J
b111100001000001111001 L
b111 .
b111 2
b11000100100010100001001010001001 /
b11000100100010100001001010001001 4
b101010110000011000000001 >
b1110111100101101110000011101111 7
b1000001111001101111000000000000 <
b111100001000001111001 8
b111100001000001111001 9
b111100001000001111001101111000 -
b111100001000001111001101111000 1
b10010 0
#29000
b110 =
b1 ;
b1000011000000100110000110000110 3
b1111011010010111111110111110110 5
b111000010010011001110001110000 6
b1011011000000100110010110 "
b1011011000000100110010110 I
b1011011000000100110010110 J
b1011011000000100110010110 L
b110 .
b110 2
b1100011010010111111100111000110 /
b1100011010010111111100111000110 4
b10111110010011100101111101111100 >
b11110111101101100110101111110000 7
b11000000100110010110110110000000 <
b1011011000000100110010110 8
b1011011000000100110010110 9
b1011011000000100110010110110110 -
b1011011000000100110010110110110 1
b10011 0
#30000
1!
b1010 =
b10100000001010000000000101000 3
b11011111011111111101111110111110 5
b11001011011110101101111110010110 6
b0 "
b0 I
b0 :
b0 J
b0 L
b1101 .
b1101 2
b10101000011111101110100101010 /
b10101000011111101110100101010 4
b11110011100001001101111111100110 >
b11001001011001010010010110010010 7
b11010100000010101111000000000000 <
b1101111001110101000000 8
b11111111111101111001110101000000 9
b11011110011101010000001010111100 -
b11011110011101010000001010111100 1
b10100 0
#31000
0!
b101 =
b100100100000000000000001 3
b11111010111101111111111111110101 5
b11111010011001011111111111110100 6
b10010111101111100111000100000 "
b10010111101111100111000100000 I
b10010111101111100111000100000 J
b10010111101111100111000100000 L
b101 .
b101 2
b1000010111100100100000110000101 /
b1000010111100100100000110000101 4
b11111011100010011111111111110110 >
b1110101101001010111110011101100 7
b10010111101111100111000100000 <
b101110001001011110111110011 8
b11111101110001001011110111110011 9
b10111000100101111011111001110001 -
b10111000100101111011111001110001 1
b10101 0
#32000
1!
b11010 =
b11101000001000010000000111010 3
b10011101110011100111001100111011 5
b10000000110010100101001100000001 6
b0 "
b0 I
b0 J
b0 L
b1100 .
b1100 2
b11101000001100011001100111010 /
b11101000001100011001100111010 4
b10111010110100101001001101110101 >
b10000000110001100010110100000001 7
b11101100000000000000000000000000 <
b100111 8
b11111111111111111111111111100111 9
b10011101110011000110000000111011 -
b10011101110011000110000000111011 1
b10110 0
#33000
0!
b10001 =
b1000100010000000101100010001 3
b1111010111110111101101111110101 5
b1110010011100111101000011100100 6
b10010001110100001010111100100100 "
b10010001110100001010111100100100 I
b1 :
b10010001110100001010111100100100 J
b10010001110100001010111100100100 L
b1 .
b1 2
b1111000110110011001101111110001 /
b1111000110110011001101111110001 4
b10000011100000111110011100000110 >
b10010001110100001010111100100100 7
b10010110001010100000000000000000 <
b10101010101 8
b10101010101 9
b1010101010100100101100010101 -
b1010101010100100101100010101 1
b10111 0
#34000
1!
b1100 =
b0 ;
b0 :
b100000001000010000001101000000 3
b110111001101111111111101101110 5
b10111000101101111110000101110 6
b0 "
b0 I
b0 J
b0 L
b1001 .
b1001 2
b100110001101011111101101001100 /
b100110001101011111101101001100 4
b1010111010110010000001010101110 >
b1010111011010000110000010110 7
b110000011101100010000000000000 <
b110001001000110000 8
b110001001000110000 9
b110001001000110000011101100010 -
b110001001000110000011101100010 1
b11000 0
#35000
b11000 =
b1 ;
b1 :
b1000100001010011010000110001000 3
b1111111111111011010100111111111 5
b111011110101000000100001110111 6
b1101 .
b1101 2
b1111100011011011010100111111000 /
b1111100011011011010100111111000 4
b11000100001001110100101110000111 >
b11001011010010111111011110010111 7
b10001111000000000000000000000000 <
b1000111 8
b1000111 9
b1000111101110011010000110001111 -
b1000111101110011010000110001111 1
b11001 0
#36000
b11100 =
b0 ;
b10001110010001000001010000011100 3
b11101111111111011101011011011111 5
b1100001101110011100001011000011 6
b0 :
b1001 .
b1001 2
b10101110011111011001010001011100 /
b10101110011111011001010001011100 4
b1111110010000011110101011111011 >
b100001010001101100001001000011 7
b11110000000000000000000000000000 <
b1100 8
b11111111111111111111111111111100 9
b11001111110001000101011010011111 -
b11001111110001000101011010011111 1
b11010 0
#37000
b1001 =
b100100011100011001000001001 3
b11100100111111100011011111001001 5
b11100000011100000000010111000000 6
b1 :
b1100 .
b1100 2
b10100100101011100011001001001001 /
b10100100101011100011001001001001 4
b11101001100011000110100111010010 >
b10100000001100000000010101000000 7
b10111100011011110001001000000000 <
b1000100110111100011011 8
b1000100110111100011011 9
b1000100110111100011011110001001 -
b1000100110111100011011110001001 1
b11011 0
#38000
0!
b10001 =
b10101000110001101100000001010001 3
b11101011111111111111110011010111 5
b1000011001110010011110010000110 6
b10010100110001101011110100101000 "
b10010100110001101011110100101000 I
b0 :
b10010100110001101011110100101000 J
b10010100110001101011110100101000 L
b0 .
b0 2
b10101000110001111111110001010001 /
b10101000110001111111110001010001 4
b10010100110001101011110100101000 >
b1000011001101101100010010000110 7
b10000001101011100000000000000000 <
b111010111111111 8
b11111111111111111111010111111111 9
b11101011111111101100000011010111 -
b11101011111111101100000011010111 1
b11100 0
#39000
b10 =
b11000100111000000000 3
b11100111001111011111111111001110 5
b11100111001100011011000111001110 6
b11100111001100011011000111001110 "
b11100111001100011011000111001110 I
b1 :
b11100111001100011011000111001110 J
b11100111001100011011000111001110 L
b100 .
b100 2
b11100001001011001100111011000010 /
b11100001001011001100111011000010 4
b11100111010010100100110111001110 >
b100100111100001011000001001010 7
b11000011101011111110000110000 <
b1100001110101111111000011 8
b1100001110101111111000011 9
b110000111010111111100001100 -
b110000111010111111100001100 1
b11101 0
#40000
b11101 =
b0 :
b11010100000100100100000110101 3
b10111111111100101111111101111111 5
b10100101011100001011011101001010 6
b1 "
b1 I
b1 ;
b1 J
b1 L
b1000 .
b1000 2
b11110111100101110110100111101 /
b11110111100101110110100111101 4
b11011010011101010100011110110100 >
b10011100100011110110110100111010 7
b11100000000000000000000000000000 <
b101 8
b11111111111111111111111111111101 9
b10111011100000100101101001110111 -
b10111011100000100101101001110111 1
b11110 0
#41000
b1011111100000101000 8
b11111111111111011111100000101000 9
b1101 =
b110110000001010000000001101100 3
b10111111111001011000000101111111 5
b10001001111000001000000100010011 6
b10111111111001011000000101111111 "
b10111111111001011000000101111111 I
b10111111111001011000000101111111 J
b10111111111001011000000101111111 L
b11 .
b11 2
b110110111001011000000101101101 /
b110110111001011000000101101101 4
b11110101111010101000000111101011 >
b10001000000111110111111100010001 7
b10100000000011111100000000000000 <
b10111111000001010000000001111110 -
b10111111000001010000000001111110 1
b11111 0
#42000
b11101111111110111111111111011111 "
b11101111111110111111111111011111 I
b10011 =
b0 ;
b1001110000101000011000010011 3
b11101111111110111111111111011111 5
b11100110001110010111100111001100 6
b1 :
b11101111111110111111111111011111 J
b11101111111110111111111111011111 L
b11101001111010111111011011010011 /
b11101001111010111111011011010011 4
b11111001101111101000010111110010 >
b100101111001101001100001001100 7
b1111000111110000000000000000000 <
b111111010 8
b111111010 9
b1111110100101000111100011111 -
b1111110100101000111100011111 1
b100000 0
#43000
b10111101110111101101100101111011 "
b10111101110111101101100101111011 I
b11011 =
b0 :
b101100000100000000100001011000 3
b10111101110111101101100101111011 5
b10010001110011101101000100100011 6
b1 ;
b10111101110111101101100101111011 J
b10111101110111101101100101111011 L
b101101110110100101100101011011 /
b101101110110100101100101011011 4
b11101001111011101110000111010011 >
b10001110001110100010111100011101 7
b11000000000000000000000000000000 <
b10111 8
b11111111111111111111111111110111 9
b10111100000101001000100001111000 -
b10111100000101001000100001111000 1
b100001 0
#44000
b1010 =
b10101000000001010111000101010 3
b10011111111111101010111100111111 5
b10001010111111100000000100010101 6
b10101000000001010111000101010 "
b10101000000001010111000101010 I
b10101000000001010111000101010 J
b10101000000001010111000101010 L
b10 .
b10 2
b10101000011001010111100101010 /
b10101000011001010111100101010 4
b10110100111111110101110101101001 >
b10001010111001011111111100010101 7
b11001010101110001111110000000000 <
b1001111111110010101011 8
b11111111111001111111110010101011 9
b10011111111100101010111000111111 -
b10011111111100101010111000111111 1
b100010 0
#45000
b1110 =
b1 :
b11000011000110100000100010000110 3
b11000111001111110011110010001110 5
b100001001010011010000001000 6
b10001010010110010100010100010100 "
b10001010010110010100010100010100 I
b10001010010110010100010100010100 J
b10001010010110010100010100010100 L
b0 .
b0 2
b11000111000110100000110010001110 /
b11000111000110100000110010001110 4
b10001010010110010100010100010100 >
b11111100001001010010101111111000 7
b11001110001000011000000000000000 <
b110000110011111100 8
b11111111111111110000110011111100 9
b11000011001111110011100010000110 -
b11000011001111110011100010000110 1
b100011 0
#46000
b110 =
b10001001101011001100000100010 3
b11111111011111011011110111111110 5
b11101110010010000010010111011100 6
b1001101011001100111111010000000 "
b1001101011001100111111010000000 I
b0 ;
b1001101011001100111111010000000 J
b1001101011001100111111010000000 L
b101 .
b101 2
b10010011011111011011110000100110 /
b10010011011111011011110000100110 4
b10000101100110101011000100000 >
b11101001101101111101110111010100 7
b1001101011001100111111010000000 <
b1111101001101011001100111 8
b1111101001101011001100111 9
b1111101001101011001100111111010 -
b1111101001101011001100111111010 1
b100100 0
#47000
b1111 =
b10010001100010011010000000100011 3
b11010111100110111011110010101111 5
b1000110000100100001110010001100 6
b11111111111111111010001100010111 "
b11111111111111111010001100010111 I
b0 :
b11111111111111111010001100010111 J
b11111111111111111010001100010111 L
b111 .
b111 2
b10010111100110011010100000101111 /
b10010111100110011010100000101111 4
b1101001001001010101110011010010 >
b111001111100100000110001110100 7
b11011010010100011000000000000000 <
b11010001100010111 8
b11111111111111111010001100010111 9
b11010001100010111011010010100011 -
b11010001100010111011010010100011 1
b100101 0
#48000
b100 =
b1 ;
b100010000010000000010001000100 3
b10101111111110010101111101011111 5
b10001101111100010101101100011011 6
b10001101101011110100100100011011 "
b10001101101011110100100100011011 I
b10001101101011110100100100011011 J
b10001101101011110100100100011011 L
b1 .
b1 2
b100010001010010000110101000100 /
b100010001010010000110101000100 4
b11010010000000010110001110100011 >
b10001101101011110100100100011011 7
b11111101100001010110010111110000 <
b1010111111011000010101100101 8
b11111010111111011000010101100101 9
b10101111110110000101011001011111 -
b10101111110110000101011001011111 1
b100110 0
#49000
b110 =
b1 :
b11100001000010010001001011000010 3
b11110111100110110011111011101111 5
b10110100100100010110000101101 6
b10110100100100010110000101101 "
b10110100100100010110000101101 I
b10110100100100010110000101101 J
b10110100100100010110000101101 L
b100 .
b100 2
b11110011000010010001101011100110 /
b11110011000010010001101011100110 4
b11011000101001000101000110110001 >
b11110010100100100001101111100101 7
b1100110110011011011001011000000 <
b11100101100110110011011011 8
b11111111100101100110110011011011 9
b11100101100110110011011011001011 -
b11100101100110110011011011001011 1
b100111 0
